aumiao/__init__.py
aumiao/api/__init__.py
aumiao/api/auth.py
aumiao/api/coco.py
aumiao/api/codegame.py
aumiao/api/community.py
aumiao/api/edu.py
aumiao/api/forum.py
aumiao/api/library.py
aumiao/api/pickduck.py
aumiao/api/shop.py
aumiao/api/user.py
aumiao/api/whale.py
aumiao/api/work.py
aumiao/core/__init__.py
aumiao/core/base.py
aumiao/core/cloudcfg.py
aumiao/core/compile.py
aumiao/core/convert.py
aumiao/core/deepser.py
aumiao/core/editorkf.py
aumiao/core/editorkn.py
aumiao/core/process.py
aumiao/core/retrieve.py
aumiao/core/services.py
aumiao/utils/__init__.py
aumiao/utils/acquire.py
aumiao/utils/data.py
aumiao/utils/decorator.py
aumiao/utils/file.py
aumiao/utils/plugin.py
aumiao/utils/tool.py
aumiao-2.6.0.dist-info/METADATA
aumiao-2.6.0.dist-info/WHEEL
aumiao-2.6.0.dist-info/entry_points.txt
aumiao-2.6.0.dist-info/RECORD
