Metadata-Version: 2.4
Name: aumiao
Version: 2.6.0
Summary: 赋能编程猫社区脚本开发 - https://aumiao.aurzex.top
Project-URL: Homepage, https://aumiao.aurzex.top
Project-URL: Documentation, https://docs.aumiao.aurzex.top
Project-URL: Repository, https://github.com/aurzex/aumiao
Project-URL: Issues, https://github.com/aurzex/aumiao/issues
Project-URL: Changelog, https://github.com/aurzex/aumiao/releases
Project-URL: Bug Tracker, https://github.com/aurzex/aumiao/issues
Author: Aurzex, MiTao, MoonLeaaaf, Nomen
Author-email: Aumiao Team <aumiao@aurzex.top>, DontLoveBy <laya200900@outlook.com>
Maintainer-email: Aumiao Team <aumiao@aurzex.top>
License: GNU General Public License v3.0 or later
Keywords: aumiao,automation,bcm,codemao,development,script
Classifier: Development Status :: 5 - Production/Stable
Classifier: Intended Audience :: Developers
Classifier: License :: OSI Approved :: GNU General Public License v3 or later (GPLv3+)
Classifier: Operating System :: OS Independent
Classifier: Programming Language :: Python :: 3
Classifier: Programming Language :: Python :: 3.12
Classifier: Programming Language :: Python :: 3.13
Classifier: Programming Language :: Python :: 3.14
Classifier: Topic :: Software Development :: Libraries :: Python Modules
Classifier: Topic :: Utilities
Requires-Python: <3.15,>=3.12
Requires-Dist: cryptography>=46.0.3
Requires-Dist: httpx>=0.28.1
Requires-Dist: websocket-client>=1.9.0
Provides-Extra: dev
Requires-Dist: black>=25.0.0; extra == 'dev'
Requires-Dist: nuitka>=2.0.0; extra == 'dev'
Requires-Dist: pytest>=9.0.0; extra == 'dev'
Requires-Dist: ruff>=0.4.0; extra == 'dev'
